polardns/__init__.py
polardns/consts.py
polardns/core.py
polardns/nfz.py
polardns/polardns.toml
polardns/polardns_real.py
polardns/modules/__init__.py
polardns/modules/a.toml
polardns/modules/add.toml
polardns/modules/adrr.toml
polardns/modules/afuzz1.toml
polardns/modules/afuzz2.toml
polardns/modules/alias.toml
polardns/modules/always.toml
polardns/modules/anrr.toml
polardns/modules/aurr.toml
polardns/modules/badcompress1.toml
polardns/modules/badcompress2.toml
polardns/modules/badcompressfwptr1.toml
polardns/modules/badcompressfwptr2.toml
polardns/modules/badcompressloop1.toml
polardns/modules/badcompressloop2.toml
polardns/modules/badcompressloop3.toml
polardns/modules/badcompressloop4.toml
polardns/modules/badcompressloop5.toml
polardns/modules/badcompressmid1.toml
polardns/modules/bigbintxt.toml
polardns/modules/bigtxt.toml
polardns/modules/chain.toml
polardns/modules/close.toml
polardns/modules/cnalias.toml
polardns/modules/cnchain.toml
polardns/modules/cnk.toml
polardns/modules/cnloop.toml
polardns/modules/count.toml
polardns/modules/cut.toml
polardns/modules/dnalias.toml
polardns/modules/dnchain.toml
polardns/modules/dnloop.toml
polardns/modules/empty1.toml
polardns/modules/empty2.toml
polardns/modules/empty3.toml
polardns/modules/empty4.toml
polardns/modules/empty5.toml
polardns/modules/empty6.toml
polardns/modules/empty7.toml
polardns/modules/fc.toml
polardns/modules/flgs.toml
polardns/modules/htalias.toml
polardns/modules/htchain.toml
polardns/modules/htloop.toml
polardns/modules/inja.toml
polardns/modules/injaaaa.toml
polardns/modules/injcname.toml
polardns/modules/injdname.toml
polardns/modules/injmx.toml
polardns/modules/injns.toml
polardns/modules/injptr.toml
polardns/modules/len.toml
polardns/modules/loop.toml
polardns/modules/manybintxt.toml
polardns/modules/manytxt.toml
polardns/modules/mxalias.toml
polardns/modules/mxchain.toml
polardns/modules/mxloop.toml
polardns/modules/nc.toml
polardns/modules/newid.toml
polardns/modules/nfz.toml
polardns-1.6.6.dist-info/licenses/LICENSE
polardns-1.6.6.dist-info/METADATA
polardns-1.6.6.dist-info/WHEEL
polardns-1.6.6.dist-info/entry_points.txt
polardns-1.6.6.dist-info/top_level.txt
polardns-1.6.6.dist-info/RECORD
