Metadata-Version: 2.4
Name: polardns
Version: 1.6.6
Summary: A specialized authoritative DNS server for penetration testing and vulnerability research.
Author-email: Ivan Jedek <ivan.jedek@oryxlabs.com>
Maintainer-email: Ivan Jedek <ivan.jedek@oryxlabs.com>
License: Apache-2.0
Project-URL: Homepage, https://github.com/oryxlabs/PolarDNS
Project-URL: Documentation, https://oryxlabs.github.io/PolarDNS
Project-URL: Tracker, https://github.com/oryxlabs/PolarDNS/issues
Keywords: DNS,DNS Server,Testing,Penetration Testing,Vulnerability Research,Fuzzing
Classifier: Development Status :: 5 - Production/Stable
Classifier: License :: OSI Approved :: Apache Software License
Classifier: Operating System :: OS Independent
Classifier: Programming Language :: Python :: 3
Classifier: Programming Language :: Python :: 3.11
Classifier: Programming Language :: Python :: 3.12
Classifier: Programming Language :: Python :: 3.13
Classifier: Programming Language :: Python :: 3.14
Classifier: Topic :: Internet :: Name Service (DNS)
Classifier: Topic :: System :: Networking
Classifier: Topic :: Education :: Testing
Classifier: Topic :: Security
Classifier: Environment :: Console
Requires-Python: >=3.11
License-File: LICENSE
Dynamic: license-file
